tesseral_fastapi/__init__.py
tesseral_fastapi/_access_token_authenticator.py
tesseral_fastapi/_auth.py
tesseral_fastapi/_credentials.py
tesseral_fastapi/_errors.py
tesseral_fastapi/_middleware.py
tesseral_fastapi/py.typed
tesseral_fastapi-0.0.3.dist-info/METADATA
tesseral_fastapi-0.0.3.dist-info/WHEEL
tesseral_fastapi-0.0.3.dist-info/RECORD
